q1/__init__.py
q1/api.py
q1/cli.py
q1/crypto.py
q1/errors.py
q1/models.py
q1/_internal/__init__.py
q1/_internal/db.py
q1/_internal/fs.py
q1/_internal/schema.sql
q1/_internal/utils.py
q1/tests/__init__.py
q1/tests/conftest.py
q1/tests/test_api.py
q1/tests/test_crypto.py
q1/tests/test_db.py
q1/tests/test_errors.py
q1/tests/test_fs.py
q1/tests/test_models.py
q1/tests/test_utils.py
q1_storage-0.1.0.dist-info/licenses/LICENSE
q1_storage-0.1.0.dist-info/WHEEL
q1_storage-0.1.0.dist-info/METADATA
q1_storage-0.1.0.dist-info/RECORD
