Metadata-Version: 2.4
Name: q1-storage
Version: 0.1.0
Summary: Simple local file storage backed by SQLite with optional AES-GCM encryption
Author: Q1 Team
Requires-Python: >=3.9
Classifier: Development Status :: 4 - Beta
Classifier: Intended Audience :: Developers
Classifier: License :: OSI Approved :: MIT License
Classifier: Programming Language :: Python :: 3
Classifier: Programming Language :: Python :: 3.9
Classifier: Programming Language :: Python :: 3.10
Classifier: Programming Language :: Python :: 3.11
Classifier: Programming Language :: Python :: 3.12
Classifier: Topic :: Software Development :: Libraries
Classifier: Topic :: System :: Filesystems
License-File: LICENSE
Requires-Dist: cryptography>=36.0.0 ; extra == "crypto"
Requires-Dist: pytest>=7.0.0 ; extra == "dev"
Requires-Dist: pytest-cov>=4.0.0 ; extra == "dev"
Requires-Dist: black>=23.0.0 ; extra == "dev"
Requires-Dist: ruff>=0.0.1 ; extra == "dev"
Requires-Dist: mypy>=1.0.0 ; extra == "dev"
Requires-Dist: sphinx>=6.0.0 ; extra == "dev"
Requires-Dist: sphinx-rtd-theme>=1.0.0 ; extra == "dev"
Provides-Extra: crypto
Provides-Extra: dev
